avea/__init__.py
avea/avea.py
avea-1.6.1.dist-info/licenses/LICENSE
avea-1.6.1.dist-info/METADATA
avea-1.6.1.dist-info/WHEEL
avea-1.6.1.dist-info/top_level.txt
avea-1.6.1.dist-info/RECORD
