Metadata-Version: 2.4
Name: avea
Version: 1.6.1
Summary: Control an Elgato Avea bulb using python3
Home-page: https://github.com/k0rventen/avea
Author: k0rventen
License: MIT
Classifier: Programming Language :: Python :: 3
Classifier: Programming Language :: Python :: 3.9
Classifier: Programming Language :: Python :: 3.10
Classifier: Programming Language :: Python :: 3.11
Classifier: Programming Language :: Python :: 3.12
Classifier: License :: OSI Approved :: MIT License
Classifier: Operating System :: POSIX :: Linux
Requires-Python: >=3.9,<4
License-File: LICENSE
Requires-Dist: bleak>=1.0.0
Requires-Dist: bleak-retry-connector>=4.4.3
Dynamic: author
Dynamic: classifier
Dynamic: description
Dynamic: description-content-type
Dynamic: home-page
Dynamic: license
Dynamic: license-file
Dynamic: requires-dist
Dynamic: requires-python
Dynamic: summary
